textutil_ja
