Metadata-Version: 1.0
Name: textutil-ja
Version: 0.1.1
Summary: textutil_ja - helpers for handling japanese text
Home-page: http://code.google.com/p/textutil_ja/
Author: Chihio Sakatoku
Author-email: csakatoku@gmail.com
License: MIT License
Platform: any
Classifier: Development Status :: 3 - Alpha
Classifier: License :: OSI Approved :: MIT License
Classifier: Programming Language :: Python
